{
    "container_type": "Publication",
    "source": "AUTHOR_PUBLICATION_ENTRY",
    "bib": {
        "title": "Hyperspectral imagery and urban areas: results of the HYEP project",
        "pub_year": 2022,
        "author": "C. WEBER and X. BRIOTTET and T. HOUET and S. GADAL and R. AGUEJDAD and Y. DEVILLE and M. DALLA MURA and C. MALLET and A. LE BRIS and M. S. KAROUI and F. Z. BENHALOUCHE and K. DJERRIRI and S. FABRE and J. AVAL",
        "journal": "Revue Française de Photogrammétrie et de Télédétection"
    }
}